{
    "Ar36": {
        "error": 0.0002977018161057382,
        "filter_outliers_dict": {
            "filter_outliers": true,
            "iterations": 1,
            "std_devs": 2
        },
        "fit": "Parabolic",
        "fn": 379,
        "include_baseline_error": false,
        "n": 400,
        "reviewed": true,
        "value": 0.0165287057436779
    },
    "Ar37": {
        "error": 0.005292004588818072,
        "filter_outliers_dict": {
            "filter_outliers": true,
            "iterations": 1,
            "std_devs": 2
        },
        "fit": "Linear",
        "fn": 383,
        "include_baseline_error": false,
        "n": 400,
        "reviewed": true,
        "value": 0.22550339197954747
    },
    "Ar38": {
        "error": 0.02650735022489239,
        "filter_outliers_dict": {
            "filter_outliers": true,
            "iterations": 1,
            "std_devs": 2
        },
        "fit": "Linear",
        "fn": 386,
        "include_baseline_error": false,
        "n": 400,
        "reviewed": true,
        "value": 0.42038586038172887
    },
    "Ar39": {
        "error": 0.010163204228577485,
        "filter_outliers_dict": {
            "filter_outliers": true,
            "iterations": 1,
            "std_devs": 2
        },
        "fit": "Parabolic",
        "fn": 380,
        "include_baseline_error": false,
        "n": 400,
        "reviewed": true,
        "value": 13.457269274261371
    },
    "Ar40": {
        "error": 0.08269987739186979,
        "filter_outliers_dict": {
            "filter_outliers": true,
            "iterations": 1,
            "std_devs": 2
        },
        "fit": "Parabolic",
        "fn": 384,
        "include_baseline_error": false,
        "n": 400,
        "reviewed": true,
        "value": 3253.6835574011648
    },
    "Ar41": {
        "error": 0.11528036808085744,
        "fit": "average_SEM",
        "value": 0.019164318536859355
    }
}